[
    {
        "distance": 2.7175371646881104, 
        "weights": {
            "Corder": true, 
            "__ndarray__": [
                [
                    1.3280164424843, 
                    4.321700737326393, 
                    2.771485539248898, 
                    3.8317944383591755, 
                    2.435218540513851, 
                    4.6480375194210675, 
                    1.582043850297038
                ], 
                [
                    4.341793464356325, 
                    2.40947165655449, 
                    1.8784998632327943, 
                    3.6335802058116595, 
                    2.379565287851632, 
                    2.72298054140781, 
                    4.985945485278068
                ], 
                [
                    3.180287962374096, 
                    4.817692616839432, 
                    2.3301480050174215, 
                    2.6822125238171495, 
                    4.531196945531067, 
                    1.5507779477576404, 
                    0.42852041777918126
                ]
            ], 
            "dtype": "float64", 
            "shape": [
                3, 
                7
            ]
        }
    }, 
    {
        "distance": 1.4891948699951172, 
        "weights": {
            "Corder": true, 
            "__ndarray__": [
                [
                    2.20108105554295, 
                    4.678667331732878, 
                    3.707617205137784, 
                    3.0799155032123346, 
                    3.895052919766135, 
                    2.425583565848568, 
                    1.315314984121645
                ], 
                [
                    1.5195764304411263, 
                    1.1669565538574407, 
                    2.6014681264443986, 
                    0.7883127318510924, 
                    4.471185825466955, 
                    1.887034202004566, 
                    2.3358355553406014
                ], 
                [
                    3.2653088076779677, 
                    2.79640046178711, 
                    1.5111818722577364, 
                    0.5753392984140817, 
                    4.857639664809926, 
                    1.0571798452480563, 
                    3.9650120356622995
                ]
            ], 
            "dtype": "float64", 
            "shape": [
                3, 
                7
            ]
        }
    }, 
    {
        "distance": 1.3713946342468262, 
        "weights": {
            "Corder": true, 
            "__ndarray__": [
                [
                    2.2104843037655804, 
                    1.546691425332138, 
                    1.0372364008677182, 
                    1.4395877877527996, 
                    4.531116556345938, 
                    3.501971574717246, 
                    0.43602826928715865
                ], 
                [
                    1.7469133293261745, 
                    0.4276697891909814, 
                    0.8821040077119435, 
                    1.375518624611502, 
                    2.051786616383649, 
                    2.8832690120966973, 
                    2.56712794382099
                ], 
                [
                    4.8064800633345275, 
                    0.4930026731462295, 
                    2.6262975253634595, 
                    0.8936172759573868, 
                    1.3969745146247903, 
                    1.8262244649022037, 
                    0.5119003590010024
                ]
            ], 
            "dtype": "float64", 
            "shape": [
                3, 
                7
            ]
        }
    }, 
    {
        "distance": 1.0701788663864136, 
        "weights": {
            "Corder": true, 
            "__ndarray__": [
                [
                    2.643033545238559, 
                    2.008366060132251, 
                    2.057986902208284, 
                    1.947242332182616, 
                    4.304032709940249, 
                    2.3711621842932873, 
                    0.16491639747775788
                ], 
                [
                    4.704975171644214, 
                    3.6141186836821655, 
                    0.5186134634306605, 
                    3.3828361630199444, 
                    1.3043827310284695, 
                    0.793868584692321, 
                    3.80918194161155
                ], 
                [
                    2.834036656628914, 
                    2.70696065497471, 
                    0.7971567082216452, 
                    1.314611031264084, 
                    0.6826401873824339, 
                    0.804498238828158, 
                    2.6928715673643144
                ]
            ], 
            "dtype": "float64", 
            "shape": [
                3, 
                7
            ]
        }
    }, 
    {
        "distance": 0.8733288049697876, 
        "weights": {
            "Corder": true, 
            "__ndarray__": [
                [
                    1.1067979560470653, 
                    2.4790525495228763, 
                    2.4039789587663623, 
                    4.128359219235078, 
                    2.719684291375342, 
                    2.198322901874645, 
                    4.464458699141206
                ], 
                [
                    2.281698626502262, 
                    1.5700643450947656, 
                    1.4545414991834527, 
                    3.773596061701601, 
                    1.0617453020601109, 
                    3.1549079753078746, 
                    4.080236787828418
                ], 
                [
                    3.768703571023535, 
                    2.1111827706422996, 
                    0.13899941161987006, 
                    4.224975422558307, 
                    3.104959292742003, 
                    1.131976683888285, 
                    0.3580391781318276
                ]
            ], 
            "dtype": "float64", 
            "shape": [
                3, 
                7
            ]
        }
    }, 
    {
        "distance": 0.8312250375747681, 
        "weights": {
            "Corder": true, 
            "__ndarray__": [
                [
                    4.508522512696229, 
                    1.065691061851911, 
                    3.8853131819888116, 
                    2.9022910550116796, 
                    2.046753754297396, 
                    1.00690401699215, 
                    3.4633633370909065
                ], 
                [
                    3.639425227454695, 
                    2.1135711366183365, 
                    1.7543561979813203, 
                    0.9627705760891125, 
                    1.4948013673031517, 
                    3.8005860156251177, 
                    1.7302338840863618
                ], 
                [
                    0.8911964942782613, 
                    2.414430409792569, 
                    0.7899521808945864, 
                    2.016941363232444, 
                    3.1909523824941672, 
                    2.018130719678124, 
                    4.896933833854658
                ]
            ], 
            "dtype": "float64", 
            "shape": [
                3, 
                7
            ]
        }
    }, 
    {
        "distance": 0.8219631910324097, 
        "weights": {
            "Corder": true, 
            "__ndarray__": [
                [
                    4.508522512696229, 
                    1.065691061851911, 
                    4.172236821835912, 
                    2.9022910550116796, 
                    2.046753754297396, 
                    1.00690401699215, 
                    3.4633633370909065
                ], 
                [
                    3.639425227454695, 
                    2.1135711366183365, 
                    1.893996471886687, 
                    0.9627705760891125, 
                    1.6907140184441478, 
                    3.8005860156251177, 
                    2.122031066349404
                ], 
                [
                    0.8911964942782613, 
                    2.414430409792569, 
                    0.7611194166958624, 
                    2.016941363232444, 
                    3.3259138235482935, 
                    2.018130719678124, 
                    4.896933833854658
                ]
            ], 
            "dtype": "float64", 
            "shape": [
                3, 
                7
            ]
        }
    }, 
    {
        "distance": 0.8199858665466309, 
        "weights": {
            "Corder": true, 
            "__ndarray__": [
                [
                    2.20108105554295, 
                    4.678667331732878, 
                    3.707617205137784, 
                    3.0799155032123346, 
                    3.895052919766135, 
                    2.425583565848568, 
                    1.315314984121645
                ], 
                [
                    1.5195764304411263, 
                    1.1669565538574407, 
                    2.6014681264443986, 
                    0.7883127318510924, 
                    4.337122850545928, 
                    2.154148124304437, 
                    2.3358355553406014
                ], 
                [
                    3.2653088076779677, 
                    2.79640046178711, 
                    1.8897430043752923, 
                    0.8217313644059856, 
                    5.042751235930824, 
                    1.0571798452480563, 
                    3.9650120356622995
                ]
            ], 
            "dtype": "float64", 
            "shape": [
                3, 
                7
            ]
        }
    }, 
    {
        "distance": 0.8138747215270996, 
        "weights": {
            "Corder": true, 
            "__ndarray__": [
                [
                    2.0419886955226048, 
                    4.678667331732878, 
                    3.707617205137784, 
                    3.0799155032123346, 
                    3.895052919766135, 
                    2.425583565848568, 
                    1.315314984121645
                ], 
                [
                    1.5195764304411263, 
                    1.1669565538574407, 
                    2.6014681264443986, 
                    1.0762991038138794, 
                    4.337122850545928, 
                    1.887034202004566, 
                    2.3358355553406014
                ], 
                [
                    3.2653088076779677, 
                    2.79640046178711, 
                    1.929522166573509, 
                    0.9893931059271427, 
                    4.857639664809926, 
                    1.0571798452480563, 
                    3.9650120356622995
                ]
            ], 
            "dtype": "float64", 
            "shape": [
                3, 
                7
            ]
        }
    }, 
    {
        "distance": 0.7337048649787903, 
        "weights": {
            "Corder": true, 
            "__ndarray__": [
                [
                    4.541204281657903, 
                    3.81919327218021, 
                    1.7685350294575004, 
                    0.13633260014650483, 
                    3.531365479382724, 
                    2.5462721755260316, 
                    0.3949073961985772
                ], 
                [
                    3.0773700445382426, 
                    0.07817488139445383, 
                    4.6313429054270445, 
                    0.6252278659274269, 
                    2.9342926908334954, 
                    4.485439419029848, 
                    1.8023521595740943
                ], 
                [
                    2.602313421919588, 
                    4.1632981769551005, 
                    1.9072852410474366, 
                    2.2956579112650584, 
                    1.6743867534512302, 
                    0.866883827353585, 
                    1.9971145475659218
                ]
            ], 
            "dtype": "float64", 
            "shape": [
                3, 
                7
            ]
        }
    }, 
    {
        "distance": 0.0030465347226709127, 
        "weights": {
            "Corder": true, 
            "__ndarray__": [
                [
                    4.595570097278578, 
                    4.766124655087727, 
                    3.731876356565043, 
                    3.6954321768485405, 
                    0.190816378330958, 
                    3.1604475535867316, 
                    2.532991413552852
                ], 
                [
                    4.916747885423397, 
                    3.857267412125908, 
                    1.0772202720103319, 
                    3.843103387739336, 
                    4.56297598717579, 
                    3.5405313112001684, 
                    0.8719904263072931
                ], 
                [
                    2.2496481104888026, 
                    1.6416083111006619, 
                    1.0106220884171875, 
                    2.7394925599614206, 
                    4.438577801567784, 
                    1.5825760367641388, 
                    1.126051296740875
                ]
            ], 
            "dtype": "float64", 
            "shape": [
                3, 
                7
            ]
        }
    }
]